ailingbot/__init__.py
ailingbot/channels/__init__.py
ailingbot/channels/channel.py
ailingbot/channels/dingtalk/__init__.py
ailingbot/channels/dingtalk/agent.py
ailingbot/channels/dingtalk/render.py
ailingbot/channels/dingtalk/webhook.py
ailingbot/channels/feishu/__init__.py
ailingbot/channels/feishu/agent.py
ailingbot/channels/feishu/render.py
ailingbot/channels/feishu/webhook.py
ailingbot/channels/slack/__init__.py
ailingbot/channels/slack/agent.py
ailingbot/channels/slack/webhook.py
ailingbot/channels/wechatwork/__init__.py
ailingbot/channels/wechatwork/agent.py
ailingbot/channels/wechatwork/encrypt.py
ailingbot/channels/wechatwork/render.py
ailingbot/channels/wechatwork/webhook.py
ailingbot/chat/__init__.py
ailingbot/chat/chatbot.py
ailingbot/chat/messages.py
ailingbot/chat/policies/__init__.py
ailingbot/chat/policies/conversation.py
ailingbot/chat/policies/document_qa.py
ailingbot/chat/policy.py
ailingbot/cli/__init__.py
ailingbot/cli/cli.py
ailingbot/cli/options.py
ailingbot/cli/render.py
ailingbot/config.py
ailingbot/endpoint/__init__.py
ailingbot/endpoint/model.py
ailingbot/endpoint/server.py
ailingbot/shared/__init__.py
ailingbot/shared/abc.py
ailingbot/shared/errors.py
ailingbot/shared/misc.py
ailingbot-0.0.8.dist-info/LICENSE
ailingbot-0.0.8.dist-info/METADATA
ailingbot-0.0.8.dist-info/WHEEL
ailingbot-0.0.8.dist-info/entry_points.txt
ailingbot-0.0.8.dist-info/RECORD
