Metadata-Version: 2.1
Name: ailingbot
Version: 0.0.8
Summary: An all-in-one solution to empower your IM bot with AI.
License: MIT
Author: ericzhang-cn
Author-email: ericzhang.buaa@gmail.com
Requires-Python: >=3.9,<4.0
Classifier: License :: OSI Approved :: MIT License
Classifier: Programming Language :: Python :: 3
Classifier: Programming Language :: Python :: 3.9
Classifier: Programming Language :: Python :: 3.10
Classifier: Programming Language :: Python :: 3.11
Requires-Dist: aiohttp[speedups] (>=3.8.3,<4.0.0)
Requires-Dist: arrow (>=1.2.3,<2.0.0)
Requires-Dist: asgiref (>=3.5.2,<4.0.0)
Requires-Dist: babel (>=2.11.0,<3.0.0)
Requires-Dist: cachetools (>=5.3.1,<6.0.0)
Requires-Dist: chromadb (>=0.3.26,<0.4.0)
Requires-Dist: click (>=8.1.3,<9.0.0)
Requires-Dist: cryptography (>=38.0.3,<39.0.0)
Requires-Dist: dynaconf (>=3.1.11,<4.0.0)
Requires-Dist: emoji (>=2.2.0,<3.0.0)
Requires-Dist: fastapi (>=0.86.0,<0.87.0)
Requires-Dist: langchain (>=0.0.214,<0.0.215)
Requires-Dist: loguru (>=0.6.0,<0.7.0)
Requires-Dist: openai (>=0.27.8,<0.28.0)
Requires-Dist: prompt-toolkit (>=3.0.33,<4.0.0)
Requires-Dist: pydantic (>=1.10.2,<2.0.0)
Requires-Dist: pypdf (>=3.11.0,<4.0.0)
Requires-Dist: rich (>=13.4.2,<14.0.0)
Requires-Dist: sqlalchemy (>=2.0.17,<3.0.0)
Requires-Dist: tabulate[widechars] (>=0.9.0,<0.10.0)
Requires-Dist: tiktoken (>=0.4.0,<0.5.0)
Requires-Dist: tomli (>=2.0.1,<3.0.0)
Requires-Dist: tomlkit (>=0.11.8,<0.12.0)
Requires-Dist: uvicorn (>=0.19.0,<0.20.0)
Requires-Dist: xmltodict (>=0.13.0,<0.14.0)
